simple_api/__init__.py
simple_api/abstract.py
simple_api/serialize.py
simple_api/urls.py
simple_api/views.py
django_very_simple_api-0.3.11.dist-info/LICENSE
django_very_simple_api-0.3.11.dist-info/METADATA
django_very_simple_api-0.3.11.dist-info/WHEEL
django_very_simple_api-0.3.11.dist-info/top_level.txt
django_very_simple_api-0.3.11.dist-info/RECORD
