Metadata-Version: 2.1
Name: django-very-simple-api
Version: 0.3.11
Summary: A Django app to quickly serialize querysets.
Home-page: https://gitlab.com/jcmcph-django/django-very-simple-api
Author: John McPherson
Author-email: UNKNOWN
License: GNU GENERAL PUBLIC LICENSE
Platform: UNKNOWN
Classifier: Environment :: Web Environment
Classifier: Framework :: Django
Classifier: Intended Audience :: Developers
Classifier: Operating System :: OS Independent
Classifier: Programming Language :: Python
Classifier: Programming Language :: Python :: 3
Classifier: Programming Language :: Python :: 3 :: Only
Classifier: Programming Language :: Python :: 3.6
Classifier: Programming Language :: Python :: 3.7
Classifier: Programming Language :: Python :: 3.8
Classifier: Topic :: Internet :: WWW/HTTP
Classifier: Topic :: Internet :: WWW/HTTP :: Dynamic Content
